docstring_parser/__init__.py
docstring_parser/attrdoc.py
docstring_parser/common.py
docstring_parser/epydoc.py
docstring_parser/google.py
docstring_parser/numpydoc.py
docstring_parser/parser.py
docstring_parser/py.typed
docstring_parser/rest.py
docstring_parser/swig.py
docstring_parser/util.py
docstring_parser/scripts/__init__.py
docstring_parser/scripts/gen_stub.py
docstring_parser_swig-0.0.3.dist-info/licenses/LICENSE.md
docstring_parser_swig-0.0.3.dist-info/METADATA
docstring_parser_swig-0.0.3.dist-info/WHEEL
docstring_parser_swig-0.0.3.dist-info/entry_points.txt
docstring_parser_swig-0.0.3.dist-info/top_level.txt
docstring_parser_swig-0.0.3.dist-info/RECORD
