Metadata-Version: 2.4
Name: docstring_parser_swig
Version: 0.0.3
Summary: Fork of docstring_parser with Swig autodoc support
Author-email: Marcin Kurczewski <dash@wind.garden>, mosamadeeb <eldeebm2002@gmail.com>
License: MIT
Project-URL: homepage, https://github.com/mosamadeeb/docstring_parser_swig
Project-URL: repository, https://github.com/mosamadeeb/docstring_parser_swig
Project-URL: changelog, https://github.com/mosamadeeb/docstring_parser_swig/blob/master/CHANGELOG.md
Classifier: Environment :: Other Environment
Classifier: Development Status :: 4 - Beta
Classifier: Intended Audience :: Developers
Classifier: License :: OSI Approved :: MIT License
Classifier: Natural Language :: English
Classifier: Operating System :: OS Independent
Classifier: Programming Language :: Python :: 3.9
Classifier: Programming Language :: Python :: 3.10
Classifier: Programming Language :: Python :: 3.11
Classifier: Programming Language :: Python :: 3.12
Classifier: Programming Language :: Python :: 3.13
Classifier: Topic :: Documentation :: Sphinx
Classifier: Topic :: Text Processing :: Markup
Classifier: Topic :: Software Development :: Libraries :: Python Modules
Requires-Python: >=3.9
License-File: LICENSE.md
Provides-Extra: test
Requires-Dist: pytest; extra == "test"
Provides-Extra: docs
Requires-Dist: pydoctor>=25.4.0; extra == "docs"
Provides-Extra: dev
Requires-Dist: docstring_parser[test]; extra == "dev"
Requires-Dist: docstring_parser[docs]; extra == "dev"
Requires-Dist: pre-commit>=2.16.0; python_version >= "3.9" and extra == "dev"
Dynamic: license-file
